<annotation>
	<folder>train</folder>
	<filename>Data_augmented290.jpg</filename>
	<path>C:\Users\Aravind GAV\Documents\project\botplant\train\Data_augmented290.jpg</path>
	<source>
		<database>Unknown</database>
	</source>
	<size>
		<width>300</width>
		<height>300</height>
		<depth>3</depth>
	</size>
	<segmented>0</segmented>
	<object>
		<name>weed</name>
		<pose>Unspecified</pose>
		<truncated>0</truncated>
		<difficult>0</difficult>
		<bndbox>
			<xmin>185</xmin>
			<ymin>108</ymin>
			<xmax>274</xmax>
			<ymax>190</ymax>
		</bndbox>
	</object>
	<object>
		<name>weed</name>
		<pose>Unspecified</pose>
		<truncated>1</truncated>
		<difficult>0</difficult>
		<bndbox>
			<xmin>139</xmin>
			<ymin>254</ymin>
			<xmax>185</xmax>
			<ymax>300</ymax>
		</bndbox>
	</object>
	<object>
		<name>weed</name>
		<pose>Unspecified</pose>
		<truncated>1</truncated>
		<difficult>0</difficult>
		<bndbox>
			<xmin>269</xmin>
			<ymin>246</ymin>
			<xmax>300</xmax>
			<ymax>280</ymax>
		</bndbox>
	</object>
	<object>
		<name>plant</name>
		<pose>Unspecified</pose>
		<truncated>0</truncated>
		<difficult>0</difficult>
		<bndbox>
			<xmin>38</xmin>
			<ymin>154</ymin>
			<xmax>120</xmax>
			<ymax>210</ymax>
		</bndbox>
	</object>
	<object>
		<name>plant</name>
		<pose>Unspecified</pose>
		<truncated>0</truncated>
		<difficult>0</difficult>
		<bndbox>
			<xmin>52</xmin>
			<ymin>17</ymin>
			<xmax>146</xmax>
			<ymax>94</ymax>
		</bndbox>
	</object>
</annotation>
